TAP/runquery.py
TAP/writerecs.cpython-37m-x86_64-linux-gnu.so
TAP/configparam.py
TAP/propfilter.py
TAP/writeresult.py
TAP/tap.py
TAP/tablenames.py
TAP/datadictionary.py
nexsciTAP-1.1.9.dist-info/RECORD
nexsciTAP-1.1.9.dist-info/LICENSE
nexsciTAP-1.1.9.dist-info/METADATA
nexsciTAP-1.1.9.dist-info/top_level.txt
nexsciTAP-1.1.9.dist-info/WHEEL
