Metadata-Version: 2.1
Name: nexsciTAP
Version: 1.1.9
Summary: NExScI VO Table Access Protocol (TAP) web service
Home-page: https://github.com/Caltech-IPAC/nexsciTAP
Author: Mihseh Kong
Author-email: mihseh@ipac.caltech.edu
License: LICENSE
Keywords: astronomy database ADQL web-service
Platform: UNKNOWN
Requires-Dist: ADQL
Requires-Dist: spatial-index
Requires-Dist: configobj
